{"name":"mydb","desc":"","tables":[{"name":"public.user","type":"BASE TABLE","comment":"","columns":[{"name":"id","type":"integer","nullable":false,"default":"nextval('user_id_seq'::regclass)","comment":""},{"name":"email","type":"text","nullable":false,"default":null,"comment":""},{"name":"name","type":"text","nullable":true,"default":null,"comment":""}],"indexes":[{"name":"user_pkey","def":"CREATE UNIQUE INDEX user_pkey ON public.\"user\" USING btree (id)","table":"public.user","columns":["id"],"comment":""},{"name":"user_email_key","def":"CREATE UNIQUE INDEX user_email_key ON public.\"user\" USING btree (email)","table":"public.user","columns":["email"],"comment":""}],"constraints":[{"name":"user_pkey","type":"PRIMARY KEY","def":"PRIMARY KEY (id)","table":"public.user","referenced_table":"","columns":["id"],"referenced_columns":[],"comment":""}],"triggers":[],"def":""},{"name":"public.post","type":"BASE TABLE","comment":"","columns":[{"name":"id","type":"integer","nullable":false,"default":"nextval('post_id_seq'::regclass)","comment":""},{"name":"title","type":"text","nullable":false,"default":null,"comment":""},{"name":"content","type":"text","nullable":true,"default":null,"comment":""},{"name":"published","type":"boolean","nullable":false,"default":"false","comment":""},{"name":"authorId","type":"integer","nullable":false,"default":null,"comment":""}],"indexes":[{"name":"post_pkey","def":"CREATE UNIQUE INDEX post_pkey ON public.post USING btree (id)","table":"public.post","columns":["id"],"comment":""}],"constraints":[{"name":"post_authorId_fkey","type":"FOREIGN KEY","def":"FOREIGN KEY (\"authorId\") REFERENCES \"user\"(id) ON UPDATE CASCADE ON DELETE RESTRICT","table":"public.post","referenced_table":"user","columns":["authorId"],"referenced_columns":["id"],"comment":""},{"name":"post_pkey","type":"PRIMARY KEY","def":"PRIMARY KEY (id)","table":"public.post","referenced_table":"","columns":["id"],"referenced_columns":[],"comment":""}],"triggers":[],"def":""}],"relations":[{"table":"public.post","columns":["authorId"],"cardinality":"Zero or more","parent_table":"public.user","parent_columns":["id"],"parent_cardinality":"Exactly one","def":"FOREIGN KEY (\"authorId\") REFERENCES \"user\"(id) ON UPDATE CASCADE ON DELETE RESTRICT","virtual":false}],"functions":[],"driver":{"name":"postgres","database_version":"PostgreSQL 16.4 (Debian 16.4-1.pgdg120+1) on x86_64-pc-linux-gnu, compiled by gcc (Debian 12.2.0-14) 12.2.0, 64-bit","meta":{"current_schema":"public","search_paths":["postgres","public"],"dict":{"Functions":"Stored procedures and functions"}}}}
